{"@t":"2019-10-08T15:53:03.2352541Z","@mt":"{StartMessage} [Timing {TimingId}]","StartMessage":"Booting Umbraco 8.1.3.","TimingId":"bb83488","SourceContext":"Umbraco.Core.Runtime.CoreRuntime","ProcessId":3928,"ProcessName":"iisexpress","ThreadId":1,"AppDomainId":2,"AppDomainAppId":"LMW3SVC2ROOT","MachineName":"DESKTOP-U4CBO3F","Log4NetLevel":"INFO ","HttpRequestNumber":1,"HttpRequestId":"1fe99e89-0b4a-4a0b-b341-51e21eaa5a76"}
{"@t":"2019-10-08T15:53:03.2521788Z","@mt":"Booting site '{HostingSiteName}', app '{HostingApplicationID}', path '{HostingPhysicalPath}', server '{MachineName}'.","HostingSiteName":"AarhusWebDevCoop","HostingApplicationID":"/LM/W3SVC/2/ROOT","HostingPhysicalPath":"C:\\Users\\Stefan\\source\\repos\\AarhusWebDevCoop\\AarhusWebDevCoop\\","MachineName":"DESKTOP-U4CBO3F","SourceContext":"Umbraco.Core.Runtime.CoreRuntime","ProcessId":3928,"ProcessName":"iisexpress","ThreadId":1,"AppDomainId":2,"AppDomainAppId":"LMW3SVC2ROOT","Log4NetLevel":"INFO ","HttpRequestNumber":1,"HttpRequestId":"1fe99e89-0b4a-4a0b-b341-51e21eaa5a76"}
{"@t":"2019-10-08T15:53:03.3460439Z","@mt":"Acquiring.","SourceContext":"Umbraco.Core.MainDom","ProcessId":3928,"ProcessName":"iisexpress","ThreadId":1,"AppDomainId":2,"AppDomainAppId":"LMW3SVC2ROOT","MachineName":"DESKTOP-U4CBO3F","Log4NetLevel":"INFO ","HttpRequestNumber":1,"HttpRequestId":"1fe99e89-0b4a-4a0b-b341-51e21eaa5a76"}
{"@t":"2019-10-08T15:53:03.3470140Z","@mt":"Acquired.","SourceContext":"Umbraco.Core.MainDom","ProcessId":3928,"ProcessName":"iisexpress","ThreadId":1,"AppDomainId":2,"AppDomainAppId":"LMW3SVC2ROOT","MachineName":"DESKTOP-U4CBO3F","Log4NetLevel":"INFO ","HttpRequestNumber":1,"HttpRequestId":"1fe99e89-0b4a-4a0b-b341-51e21eaa5a76"}
{"@t":"2019-10-08T15:53:03.8886473Z","@mt":"{StartMessage} [Timing {TimingId}]","StartMessage":"Resolving composer types.","TimingId":"da3a071","SourceContext":"Umbraco.Core.Runtime.CoreRuntime","ProcessId":3928,"ProcessName":"iisexpress","ThreadId":1,"AppDomainId":2,"AppDomainAppId":"LMW3SVC2ROOT","MachineName":"DESKTOP-U4CBO3F","Log4NetLevel":"INFO ","HttpRequestNumber":1,"HttpRequestId":"1fe99e89-0b4a-4a0b-b341-51e21eaa5a76"}
{"@t":"2019-10-08T15:53:04.0362529Z","@mt":"{EndMessage} ({Duration}ms) [Timing {TimingId}]","EndMessage":"Resolved.","Duration":147,"TimingId":"da3a071","SourceContext":"Umbraco.Core.Runtime.CoreRuntime","ProcessId":3928,"ProcessName":"iisexpress","ThreadId":1,"AppDomainId":2,"AppDomainAppId":"LMW3SVC2ROOT","MachineName":"DESKTOP-U4CBO3F","Log4NetLevel":"INFO ","HttpRequestNumber":1,"HttpRequestId":"1fe99e89-0b4a-4a0b-b341-51e21eaa5a76"}
{"@t":"2019-10-08T15:53:04.9897108Z","@mt":"Initializing Umbraco internal event handlers for cache refreshing.","SourceContext":"Umbraco.Web.Cache.DistributedCacheBinderComponent","ProcessId":3928,"ProcessName":"iisexpress","ThreadId":1,"AppDomainId":2,"AppDomainAppId":"LMW3SVC2ROOT","MachineName":"DESKTOP-U4CBO3F","Log4NetLevel":"INFO ","HttpRequestNumber":1,"HttpRequestId":"1fe99e89-0b4a-4a0b-b341-51e21eaa5a76"}
{"@t":"2019-10-08T15:53:05.0296041Z","@mt":"Adding examine event handlers for {RegisteredIndexers} index providers.","RegisteredIndexers":3,"SourceContext":"Umbraco.Web.Search.ExamineComponent","ProcessId":3928,"ProcessName":"iisexpress","ThreadId":1,"AppDomainId":2,"AppDomainAppId":"LMW3SVC2ROOT","MachineName":"DESKTOP-U4CBO3F","Log4NetLevel":"INFO ","HttpRequestNumber":1,"HttpRequestId":"1fe99e89-0b4a-4a0b-b341-51e21eaa5a76"}
{"@t":"2019-10-08T15:53:05.0775077Z","@mt":"Forcing index {IndexerName} to be unlocked since it was left in a locked state","IndexerName":"InternalIndex","SourceContext":"Umbraco.Examine.ExamineExtensions","ProcessId":3928,"ProcessName":"iisexpress","ThreadId":1,"AppDomainId":2,"AppDomainAppId":"LMW3SVC2ROOT","MachineName":"DESKTOP-U4CBO3F","Log4NetLevel":"INFO ","HttpRequestNumber":1,"HttpRequestId":"1fe99e89-0b4a-4a0b-b341-51e21eaa5a76"}
{"@t":"2019-10-08T15:53:05.0784727Z","@mt":"Forcing index {IndexerName} to be unlocked since it was left in a locked state","IndexerName":"MembersIndex","SourceContext":"Umbraco.Examine.ExamineExtensions","ProcessId":3928,"ProcessName":"iisexpress","ThreadId":1,"AppDomainId":2,"AppDomainAppId":"LMW3SVC2ROOT","MachineName":"DESKTOP-U4CBO3F","Log4NetLevel":"INFO ","HttpRequestNumber":1,"HttpRequestId":"1fe99e89-0b4a-4a0b-b341-51e21eaa5a76"}
{"@t":"2019-10-08T15:53:05.0794702Z","@mt":"Forcing index {IndexerName} to be unlocked since it was left in a locked state","IndexerName":"ExternalIndex","SourceContext":"Umbraco.Examine.ExamineExtensions","ProcessId":3928,"ProcessName":"iisexpress","ThreadId":1,"AppDomainId":2,"AppDomainAppId":"LMW3SVC2ROOT","MachineName":"DESKTOP-U4CBO3F","Log4NetLevel":"INFO ","HttpRequestNumber":1,"HttpRequestId":"1fe99e89-0b4a-4a0b-b341-51e21eaa5a76"}
{"@t":"2019-10-08T15:53:05.0794702Z","@mt":"Starting initialize async background thread.","SourceContext":"Umbraco.Web.Search.BackgroundIndexRebuilder","ProcessId":3928,"ProcessName":"iisexpress","ThreadId":1,"AppDomainId":2,"AppDomainAppId":"LMW3SVC2ROOT","MachineName":"DESKTOP-U4CBO3F","Log4NetLevel":"INFO ","HttpRequestNumber":1,"HttpRequestId":"1fe99e89-0b4a-4a0b-b341-51e21eaa5a76"}
{"@t":"2019-10-08T15:53:05.0844570Z","@mt":"{EndMessage} ({Duration}ms) [Timing {TimingId}]","EndMessage":"Booted.","Duration":1855,"TimingId":"bb83488","SourceContext":"Umbraco.Core.Runtime.CoreRuntime","ProcessId":3928,"ProcessName":"iisexpress","ThreadId":1,"AppDomainId":2,"AppDomainAppId":"LMW3SVC2ROOT","MachineName":"DESKTOP-U4CBO3F","Log4NetLevel":"INFO ","HttpRequestNumber":1,"HttpRequestId":"1fe99e89-0b4a-4a0b-b341-51e21eaa5a76"}
{"@t":"2019-10-08T15:53:05.3926910Z","@mt":"New url {Url} detected, re-discovering application url.","Url":"http://localhost:50969/umbraco","SourceContext":"Umbraco.Core.Sync.ApplicationUrlHelper","ProcessId":3928,"ProcessName":"iisexpress","ThreadId":10,"AppDomainId":2,"AppDomainAppId":"LMW3SVC2ROOT","MachineName":"DESKTOP-U4CBO3F","Log4NetLevel":"INFO ","HttpRequestNumber":2,"HttpRequestId":"20bb2d02-a096-4500-948b-96edb07f4f3f"}
{"@t":"2019-10-08T15:53:05.3936893Z","@mt":"ApplicationUrl: {UmbracoAppUrl} (UmbracoModule request)","UmbracoAppUrl":"http://localhost:50969/umbraco","SourceContext":"Umbraco.Core.Sync.ApplicationUrlHelper","ProcessId":3928,"ProcessName":"iisexpress","ThreadId":10,"AppDomainId":2,"AppDomainAppId":"LMW3SVC2ROOT","MachineName":"DESKTOP-U4CBO3F","Log4NetLevel":"INFO ","HttpRequestNumber":2,"HttpRequestId":"20bb2d02-a096-4500-948b-96edb07f4f3f"}
{"@t":"2019-10-08T15:53:20.6892204Z","@mt":"[{EventType}] Event Id: {EventId}, State: {State}","EventType":"Information","EventId":0,"State":"Login attempt succeeded for username stefanpedersen91@gmail.com from IP address ::1","SourceContext":"Umbraco.Core.Logging.OwinLogger","ProcessId":3928,"ProcessName":"iisexpress","ThreadId":13,"AppDomainId":2,"AppDomainAppId":"LMW3SVC2ROOT","MachineName":"DESKTOP-U4CBO3F","Log4NetLevel":"INFO ","HttpRequestNumber":3,"HttpRequestId":"aa580b18-93f7-40ad-a672-bf9cde199f6c"}
{"@t":"2019-10-08T15:53:20.6892204Z","@mt":"[{EventType}] Event Id: {EventId}, State: {State}","EventType":"Information","EventId":0,"State":"User: stefanpedersen91@gmail.com logged in from IP address ::1","SourceContext":"Umbraco.Core.Logging.OwinLogger","ProcessId":3928,"ProcessName":"iisexpress","ThreadId":13,"AppDomainId":2,"AppDomainAppId":"LMW3SVC2ROOT","MachineName":"DESKTOP-U4CBO3F","Log4NetLevel":"INFO ","HttpRequestNumber":3,"HttpRequestId":"aa580b18-93f7-40ad-a672-bf9cde199f6c"}
{"@t":"2019-10-08T15:54:06.0778692Z","@mt":"Scheduled health check results:","SourceContext":"Umbraco.Web.HealthCheck.HealthCheckResults","ProcessId":3928,"ProcessName":"iisexpress","ThreadId":11,"AppDomainId":2,"AppDomainAppId":"LMW3SVC2ROOT","MachineName":"DESKTOP-U4CBO3F","Log4NetLevel":"INFO "}
{"@t":"2019-10-08T15:54:06.0778692Z","@mt":"Checks for '{HealthCheckName}' all completed successfully.","HealthCheckName":"Folder & File Permissions","SourceContext":"Umbraco.Web.HealthCheck.HealthCheckResults","ProcessId":3928,"ProcessName":"iisexpress","ThreadId":11,"AppDomainId":2,"AppDomainAppId":"LMW3SVC2ROOT","MachineName":"DESKTOP-U4CBO3F","Log4NetLevel":"INFO "}
{"@t":"2019-10-08T15:54:06.0778692Z","@mt":"Result for {HealthCheckName}: {HealthCheckResult}, Message: '{HealthCheckMessage}'","HealthCheckName":"Folder & File Permissions","HealthCheckResult":"Success","HealthCheckMessage":"All folders have the correct permissions set.","SourceContext":"Umbraco.Web.HealthCheck.HealthCheckResults","ProcessId":3928,"ProcessName":"iisexpress","ThreadId":11,"AppDomainId":2,"AppDomainAppId":"LMW3SVC2ROOT","MachineName":"DESKTOP-U4CBO3F","Log4NetLevel":"INFO "}
{"@t":"2019-10-08T15:54:06.0778692Z","@mt":"Result for {HealthCheckName}: {HealthCheckResult}, Message: '{HealthCheckMessage}'","HealthCheckName":"Folder & File Permissions","HealthCheckResult":"Success","HealthCheckMessage":"All files have the correct permissions set.","SourceContext":"Umbraco.Web.HealthCheck.HealthCheckResults","ProcessId":3928,"ProcessName":"iisexpress","ThreadId":11,"AppDomainId":2,"AppDomainAppId":"LMW3SVC2ROOT","MachineName":"DESKTOP-U4CBO3F","Log4NetLevel":"INFO "}
{"@t":"2019-10-08T15:54:06.0778692Z","@mt":"Checks for '{HealthCheckName}' all completed successfully.","HealthCheckName":"SMTP Settings","SourceContext":"Umbraco.Web.HealthCheck.HealthCheckResults","ProcessId":3928,"ProcessName":"iisexpress","ThreadId":11,"AppDomainId":2,"AppDomainAppId":"LMW3SVC2ROOT","MachineName":"DESKTOP-U4CBO3F","Log4NetLevel":"INFO "}
{"@t":"2019-10-08T15:54:06.0778692Z","@mt":"Result for {HealthCheckName}: {HealthCheckResult}, Message: '{HealthCheckMessage}'","HealthCheckName":"SMTP Settings","HealthCheckResult":"Success","HealthCheckMessage":"SMTP settings are configured correctly and the service is operating as expected.","SourceContext":"Umbraco.Web.HealthCheck.HealthCheckResults","ProcessId":3928,"ProcessName":"iisexpress","ThreadId":11,"AppDomainId":2,"AppDomainAppId":"LMW3SVC2ROOT","MachineName":"DESKTOP-U4CBO3F","Log4NetLevel":"INFO "}
{"@t":"2019-10-08T15:54:06.0778692Z","@mt":"Checks for '{HealthCheckName}' completed with errors.","@l":"Warning","HealthCheckName":"Macro errors","SourceContext":"Umbraco.Web.HealthCheck.HealthCheckResults","ProcessId":3928,"ProcessName":"iisexpress","ThreadId":11,"AppDomainId":2,"AppDomainAppId":"LMW3SVC2ROOT","MachineName":"DESKTOP-U4CBO3F","Log4NetLevel":"WARN "}
{"@t":"2019-10-08T15:54:06.0778692Z","@mt":"Result for {HealthCheckName}: {HealthCheckResult}, Message: '{HealthCheckMessage}'","HealthCheckName":"Macro errors","HealthCheckResult":"Error","HealthCheckMessage":"MacroErrors are set to 'throw' which will prevent some or all pages in your site from loading completely if there are any errors in macros. Rectifying this will set the value to 'inline'.","SourceContext":"Umbraco.Web.HealthCheck.HealthCheckResults","ProcessId":3928,"ProcessName":"iisexpress","ThreadId":11,"AppDomainId":2,"AppDomainAppId":"LMW3SVC2ROOT","MachineName":"DESKTOP-U4CBO3F","Log4NetLevel":"INFO "}
{"@t":"2019-10-08T15:54:06.0778692Z","@mt":"Checks for '{HealthCheckName}' completed with errors.","@l":"Warning","HealthCheckName":"Notification Email Settings","SourceContext":"Umbraco.Web.HealthCheck.HealthCheckResults","ProcessId":3928,"ProcessName":"iisexpress","ThreadId":11,"AppDomainId":2,"AppDomainAppId":"LMW3SVC2ROOT","MachineName":"DESKTOP-U4CBO3F","Log4NetLevel":"WARN "}
{"@t":"2019-10-08T15:54:06.0778692Z","@mt":"Result for {HealthCheckName}: {HealthCheckResult}, Message: '{HealthCheckMessage}'","HealthCheckName":"Notification Email Settings","HealthCheckResult":"Error","HealthCheckMessage":"Notification email is still set to the default value of <strong>your@email.here</strong>.","SourceContext":"Umbraco.Web.HealthCheck.HealthCheckResults","ProcessId":3928,"ProcessName":"iisexpress","ThreadId":11,"AppDomainId":2,"AppDomainAppId":"LMW3SVC2ROOT","MachineName":"DESKTOP-U4CBO3F","Log4NetLevel":"INFO "}
{"@t":"2019-10-08T15:54:06.0778692Z","@mt":"Checks for '{HealthCheckName}' all completed successfully.","HealthCheckName":"Try Skip IIS Custom Errors","SourceContext":"Umbraco.Web.HealthCheck.HealthCheckResults","ProcessId":3928,"ProcessName":"iisexpress","ThreadId":11,"AppDomainId":2,"AppDomainAppId":"LMW3SVC2ROOT","MachineName":"DESKTOP-U4CBO3F","Log4NetLevel":"INFO "}
{"@t":"2019-10-08T15:54:06.0778692Z","@mt":"Result for {HealthCheckName}: {HealthCheckResult}, Message: '{HealthCheckMessage}'","HealthCheckName":"Try Skip IIS Custom Errors","HealthCheckResult":"Success","HealthCheckMessage":"Try Skip IIS Custom Errors is set to 'true' and you're using IIS version '10.0'.","SourceContext":"Umbraco.Web.HealthCheck.HealthCheckResults","ProcessId":3928,"ProcessName":"iisexpress","ThreadId":11,"AppDomainId":2,"AppDomainAppId":"LMW3SVC2ROOT","MachineName":"DESKTOP-U4CBO3F","Log4NetLevel":"INFO "}
{"@t":"2019-10-08T15:54:06.0778692Z","@mt":"Checks for '{HealthCheckName}' all completed successfully.","HealthCheckName":"Custom Errors","SourceContext":"Umbraco.Web.HealthCheck.HealthCheckResults","ProcessId":3928,"ProcessName":"iisexpress","ThreadId":11,"AppDomainId":2,"AppDomainAppId":"LMW3SVC2ROOT","MachineName":"DESKTOP-U4CBO3F","Log4NetLevel":"INFO "}
{"@t":"2019-10-08T15:54:06.0778692Z","@mt":"Result for {HealthCheckName}: {HealthCheckResult}, Message: '{HealthCheckMessage}'","HealthCheckName":"Custom Errors","HealthCheckResult":"Success","HealthCheckMessage":"Custom errors are set to 'RemoteOnly'.","SourceContext":"Umbraco.Web.HealthCheck.HealthCheckResults","ProcessId":3928,"ProcessName":"iisexpress","ThreadId":11,"AppDomainId":2,"AppDomainAppId":"LMW3SVC2ROOT","MachineName":"DESKTOP-U4CBO3F","Log4NetLevel":"INFO "}
{"@t":"2019-10-08T15:54:06.0778692Z","@mt":"Checks for '{HealthCheckName}' all completed successfully.","HealthCheckName":"Trace Mode","SourceContext":"Umbraco.Web.HealthCheck.HealthCheckResults","ProcessId":3928,"ProcessName":"iisexpress","ThreadId":11,"AppDomainId":2,"AppDomainAppId":"LMW3SVC2ROOT","MachineName":"DESKTOP-U4CBO3F","Log4NetLevel":"INFO "}
{"@t":"2019-10-08T15:54:06.0778692Z","@mt":"Result for {HealthCheckName}: {HealthCheckResult}, Message: '{HealthCheckMessage}'","HealthCheckName":"Trace Mode","HealthCheckResult":"Success","HealthCheckMessage":"Trace mode is disabled.","SourceContext":"Umbraco.Web.HealthCheck.HealthCheckResults","ProcessId":3928,"ProcessName":"iisexpress","ThreadId":11,"AppDomainId":2,"AppDomainAppId":"LMW3SVC2ROOT","MachineName":"DESKTOP-U4CBO3F","Log4NetLevel":"INFO "}
{"@t":"2019-10-08T15:54:06.0778692Z","@mt":"Checks for '{HealthCheckName}' completed with errors.","@l":"Warning","HealthCheckName":"Debug Compilation Mode","SourceContext":"Umbraco.Web.HealthCheck.HealthCheckResults","ProcessId":3928,"ProcessName":"iisexpress","ThreadId":11,"AppDomainId":2,"AppDomainAppId":"LMW3SVC2ROOT","MachineName":"DESKTOP-U4CBO3F","Log4NetLevel":"WARN "}
{"@t":"2019-10-08T15:54:06.0778692Z","@mt":"Result for {HealthCheckName}: {HealthCheckResult}, Message: '{HealthCheckMessage}'","HealthCheckName":"Debug Compilation Mode","HealthCheckResult":"Error","HealthCheckMessage":"Debug compilation mode is currently enabled. It is recommended to disable this setting before go live.","SourceContext":"Umbraco.Web.HealthCheck.HealthCheckResults","ProcessId":3928,"ProcessName":"iisexpress","ThreadId":11,"AppDomainId":2,"AppDomainAppId":"LMW3SVC2ROOT","MachineName":"DESKTOP-U4CBO3F","Log4NetLevel":"INFO "}
{"@t":"2019-10-08T15:54:06.0778692Z","@mt":"Checks for '{HealthCheckName}' completed with errors.","@l":"Warning","HealthCheckName":"Cross-site scripting Protection (X-XSS-Protection header)","SourceContext":"Umbraco.Web.HealthCheck.HealthCheckResults","ProcessId":3928,"ProcessName":"iisexpress","ThreadId":11,"AppDomainId":2,"AppDomainAppId":"LMW3SVC2ROOT","MachineName":"DESKTOP-U4CBO3F","Log4NetLevel":"WARN "}
{"@t":"2019-10-08T15:54:06.0778692Z","@mt":"Result for {HealthCheckName}: {HealthCheckResult}, Message: '{HealthCheckMessage}'","HealthCheckName":"Cross-site scripting Protection (X-XSS-Protection header)","HealthCheckResult":"Error","HealthCheckMessage":"The header <strong>X-XSS-Protection</strong> was not found.","SourceContext":"Umbraco.Web.HealthCheck.HealthCheckResults","ProcessId":3928,"ProcessName":"iisexpress","ThreadId":11,"AppDomainId":2,"AppDomainAppId":"LMW3SVC2ROOT","MachineName":"DESKTOP-U4CBO3F","Log4NetLevel":"INFO "}
{"@t":"2019-10-08T15:54:06.0778692Z","@mt":"Checks for '{HealthCheckName}' completed with errors.","@l":"Warning","HealthCheckName":"Cookie hijacking and protocol downgrade attacks Protection (Strict-Transport-Security Header (HSTS))","SourceContext":"Umbraco.Web.HealthCheck.HealthCheckResults","ProcessId":3928,"ProcessName":"iisexpress","ThreadId":11,"AppDomainId":2,"AppDomainAppId":"LMW3SVC2ROOT","MachineName":"DESKTOP-U4CBO3F","Log4NetLevel":"WARN "}
{"@t":"2019-10-08T15:54:06.0778692Z","@mt":"Result for {HealthCheckName}: {HealthCheckResult}, Message: '{HealthCheckMessage}'","HealthCheckName":"Cookie hijacking and protocol downgrade attacks Protection (Strict-Transport-Security Header (HSTS))","HealthCheckResult":"Error","HealthCheckMessage":"The header <strong>Strict-Transport-Security</strong> was not found.","SourceContext":"Umbraco.Web.HealthCheck.HealthCheckResults","ProcessId":3928,"ProcessName":"iisexpress","ThreadId":11,"AppDomainId":2,"AppDomainAppId":"LMW3SVC2ROOT","MachineName":"DESKTOP-U4CBO3F","Log4NetLevel":"INFO "}
{"@t":"2019-10-08T15:54:06.0778692Z","@mt":"Checks for '{HealthCheckName}' completed with errors.","@l":"Warning","HealthCheckName":"Content/MIME Sniffing Protection","SourceContext":"Umbraco.Web.HealthCheck.HealthCheckResults","ProcessId":3928,"ProcessName":"iisexpress","ThreadId":11,"AppDomainId":2,"AppDomainAppId":"LMW3SVC2ROOT","MachineName":"DESKTOP-U4CBO3F","Log4NetLevel":"WARN "}
{"@t":"2019-10-08T15:54:06.0778692Z","@mt":"Result for {HealthCheckName}: {HealthCheckResult}, Message: '{HealthCheckMessage}'","HealthCheckName":"Content/MIME Sniffing Protection","HealthCheckResult":"Error","HealthCheckMessage":"The header or meta-tag <strong>X-Content-Type-Options</strong> used to protect against MIME sniffing vulnerabilities was not found.","SourceContext":"Umbraco.Web.HealthCheck.HealthCheckResults","ProcessId":3928,"ProcessName":"iisexpress","ThreadId":11,"AppDomainId":2,"AppDomainAppId":"LMW3SVC2ROOT","MachineName":"DESKTOP-U4CBO3F","Log4NetLevel":"INFO "}
{"@t":"2019-10-08T15:54:06.0778692Z","@mt":"Checks for '{HealthCheckName}' all completed successfully.","HealthCheckName":"Excessive Headers","SourceContext":"Umbraco.Web.HealthCheck.HealthCheckResults","ProcessId":3928,"ProcessName":"iisexpress","ThreadId":11,"AppDomainId":2,"AppDomainAppId":"LMW3SVC2ROOT","MachineName":"DESKTOP-U4CBO3F","Log4NetLevel":"INFO "}
{"@t":"2019-10-08T15:54:06.0778692Z","@mt":"Result for {HealthCheckName}: {HealthCheckResult}, Message: '{HealthCheckMessage}'","HealthCheckName":"Excessive Headers","HealthCheckResult":"Success","HealthCheckMessage":"No headers revealing information about the website technology were found.","SourceContext":"Umbraco.Web.HealthCheck.HealthCheckResults","ProcessId":3928,"ProcessName":"iisexpress","ThreadId":11,"AppDomainId":2,"AppDomainAppId":"LMW3SVC2ROOT","MachineName":"DESKTOP-U4CBO3F","Log4NetLevel":"INFO "}
{"@t":"2019-10-08T15:54:06.0778692Z","@mt":"Checks for '{HealthCheckName}' completed with errors.","@l":"Warning","HealthCheckName":"Click-Jacking Protection","SourceContext":"Umbraco.Web.HealthCheck.HealthCheckResults","ProcessId":3928,"ProcessName":"iisexpress","ThreadId":11,"AppDomainId":2,"AppDomainAppId":"LMW3SVC2ROOT","MachineName":"DESKTOP-U4CBO3F","Log4NetLevel":"WARN "}
{"@t":"2019-10-08T15:54:06.0778692Z","@mt":"Result for {HealthCheckName}: {HealthCheckResult}, Message: '{HealthCheckMessage}'","HealthCheckName":"Click-Jacking Protection","HealthCheckResult":"Error","HealthCheckMessage":"The header or meta-tag <strong>X-Frame-Options</strong> used to control whether a site can be IFRAMEd by another was not found.","SourceContext":"Umbraco.Web.HealthCheck.HealthCheckResults","ProcessId":3928,"ProcessName":"iisexpress","ThreadId":11,"AppDomainId":2,"AppDomainAppId":"LMW3SVC2ROOT","MachineName":"DESKTOP-U4CBO3F","Log4NetLevel":"INFO "}
{"@t":"2019-10-08T15:54:06.0778692Z","@mt":"Checks for '{HealthCheckName}' completed with errors.","@l":"Warning","HealthCheckName":"HTTPS Configuration","SourceContext":"Umbraco.Web.HealthCheck.HealthCheckResults","ProcessId":3928,"ProcessName":"iisexpress","ThreadId":11,"AppDomainId":2,"AppDomainAppId":"LMW3SVC2ROOT","MachineName":"DESKTOP-U4CBO3F","Log4NetLevel":"WARN "}
{"@t":"2019-10-08T15:54:06.0778692Z","@mt":"Result for {HealthCheckName}: {HealthCheckResult}, Message: '{HealthCheckMessage}'","HealthCheckName":"HTTPS Configuration","HealthCheckResult":"Error","HealthCheckMessage":"You are currently not viewing the site using the HTTPS scheme.","SourceContext":"Umbraco.Web.HealthCheck.HealthCheckResults","ProcessId":3928,"ProcessName":"iisexpress","ThreadId":11,"AppDomainId":2,"AppDomainAppId":"LMW3SVC2ROOT","MachineName":"DESKTOP-U4CBO3F","Log4NetLevel":"INFO "}
{"@t":"2019-10-08T15:54:06.0778692Z","@mt":"Result for {HealthCheckName}: {HealthCheckResult}, Message: '{HealthCheckMessage}'","HealthCheckName":"HTTPS Configuration","HealthCheckResult":"Info","HealthCheckMessage":"The appSetting 'Umbraco.Core.UseHttps' is set to 'false' in your web.config file. Once you access this site using the HTTPS scheme, that should be set to 'true'.","SourceContext":"Umbraco.Web.HealthCheck.HealthCheckResults","ProcessId":3928,"ProcessName":"iisexpress","ThreadId":11,"AppDomainId":2,"AppDomainAppId":"LMW3SVC2ROOT","MachineName":"DESKTOP-U4CBO3F","Log4NetLevel":"INFO "}
{"@t":"2019-10-08T15:54:06.0778692Z","@mt":"Result for {HealthCheckName}: {HealthCheckResult}, Message: '{HealthCheckMessage}'","HealthCheckName":"HTTPS Configuration","HealthCheckResult":"Error","HealthCheckMessage":"Error pinging the URL https://localhost:50969/umbraco - 'Den underliggende forbindelse blev lukket: Der opstod en uventet fejl ved afsendelse..'","SourceContext":"Umbraco.Web.HealthCheck.HealthCheckResults","ProcessId":3928,"ProcessName":"iisexpress","ThreadId":11,"AppDomainId":2,"AppDomainAppId":"LMW3SVC2ROOT","MachineName":"DESKTOP-U4CBO3F","Log4NetLevel":"INFO "}
{"@t":"2019-10-08T15:54:24.9533141Z","@mt":"Document {ContentName} (id={ContentId}) has been published.","ContentName":"Memberslist","ContentId":1133,"SourceContext":"Umbraco.Core.Services.Implement.ContentService","ProcessId":3928,"ProcessName":"iisexpress","ThreadId":11,"AppDomainId":2,"AppDomainAppId":"LMW3SVC2ROOT","MachineName":"DESKTOP-U4CBO3F","Log4NetLevel":"INFO ","HttpRequestNumber":4,"HttpRequestId":"7cfeac10-f2e8-4e62-994f-2f56f2fd8079"}
